vlde/__init__.py
vlde/__version__.py
vlde/error.py
vlde/validate.py
vlde-0.3.0.dist-info/DESCRIPTION.rst
vlde-0.3.0.dist-info/METADATA
vlde-0.3.0.dist-info/RECORD
vlde-0.3.0.dist-info/WHEEL
vlde-0.3.0.dist-info/metadata.json
vlde-0.3.0.dist-info/top_level.txt
