Metadata-Version: 2.0
Name: vlde
Version: 0.3.0
Summary: A data integrity check library
Home-page: https://github.com/xiaojieluo/vlde
Author: Luo Xiaojie
Author-email: xiaojieluoff@gmail.com
License: Copyright 2017 Luo Xiaojie
